asyncio_oss/__init__.py
asyncio_oss/api.py
asyncio_oss/exceptions.py
asyncio_oss/http.py
asyncio_oss/iterators.py
asyncio_oss/models.py
asyncio_oss/utils.py
asyncio_oss-1.1.5.dist-info/LICENSE
asyncio_oss-1.1.5.dist-info/METADATA
asyncio_oss-1.1.5.dist-info/WHEEL
asyncio_oss-1.1.5.dist-info/top_level.txt
asyncio_oss-1.1.5.dist-info/RECORD
