Metadata-Version: 2.1
Name: asyncio-oss
Version: 1.1.5
Summary: An asynchronous python client SDK for OSS(Aliyun Object Storage Service).
Home-page: https://github.com/Yaocool/async-oss
Author: Ozzy
Author-email: ozzycharon@gmail.com
License: MIT
Keywords: asyncio-oss,async-oss,oss
License-File: LICENSE
Requires-Dist: aiohttp
Requires-Dist: oss2
